[
    {
        "id": "78b0f43927df8cf9",
        "type": "tab",
        "label": "SolarMeterCloud",
        "disabled": false,
        "info": "",
        "env": []
    },
    {
        "id": "6b8159ad83020446",
        "type": "function",
        "z": "78b0f43927df8cf9",
        "name": "S30001",
        "func": "var x = Math.round(msg.payload[0] * 100) / 100;\nflow.set('S30001', x);\nmsg.payload = x + ' A';\nreturn msg;",
        "outputs": 1,
        "timeout": 0,
        "noerr": 0,
        "initialize": "",
        "finalize": "",
        "libs": [],
        "x": 1100,
        "y": 940,
        "wires": [
            [
                "7c180442be53fa33"
            ]
        ]
    },
    {
        "id": "b0caa7e2d131b91a",
        "type": "comment",
        "z": "78b0f43927df8cf9",
        "name": "SolarMeter",
        "info": "",
        "x": 620,
        "y": 780,
        "wires": []
    },
    {
        "id": "8bad341de1976d49",
        "type": "function",
        "z": "78b0f43927df8cf9",
        "name": "S30007",
        "func": "var x = Math.round(msg.payload[0] * 100) / 100;\nflow.set('S30007', x);\nmsg.payload = x + ' A';\nreturn msg;",
        "outputs": 1,
        "timeout": 0,
        "noerr": 0,
        "initialize": "",
        "finalize": "",
        "libs": [],
        "x": 1040,
        "y": 1180,
        "wires": [
            [
                "2672bc5185574ca9"
            ]
        ]
    },
    {
        "id": "d50d901d9fb59818",
        "type": "function",
        "z": "78b0f43927df8cf9",
        "name": "S30013",
        "func": "var x = Math.round(msg.payload[0] * 100) / 100;\nflow.set('S30013', x);\nmsg.payload = x + ' W';\nreturn msg;",
        "outputs": 1,
        "timeout": 0,
        "noerr": 0,
        "initialize": "",
        "finalize": "",
        "libs": [],
        "x": 840,
        "y": 1540,
        "wires": [
            [
                "d481cbd4d0e9a444"
            ]
        ]
    },
    {
        "id": "8ad6361d59457335",
        "type": "function",
        "z": "78b0f43927df8cf9",
        "name": "S30073",
        "func": "var x = Math.round(msg.payload[0] * 100) / 100;\nflow.set('S30073', x);\nmsg.payload = x + ' kWh';\nreturn msg;",
        "outputs": 1,
        "timeout": 0,
        "noerr": 0,
        "initialize": "",
        "finalize": "",
        "libs": [],
        "x": 1120,
        "y": 2320,
        "wires": [
            [
                "f2db9c1245079aa9"
            ]
        ]
    },
    {
        "id": "881bf1ad6264efb3",
        "type": "function",
        "z": "78b0f43927df8cf9",
        "name": "S30071",
        "func": "var x = Math.round(msg.payload[0] * 100) / 100;\nflow.set('S30071', x);\nmsg.payload = x + ' Hz';\nreturn msg;\n",
        "outputs": 1,
        "timeout": 0,
        "noerr": 0,
        "initialize": "",
        "finalize": "",
        "libs": [],
        "x": 1020,
        "y": 2040,
        "wires": [
            [
                "5c1e9f865fa36127"
            ]
        ]
    },
    {
        "id": "d8df70aa3f514bf9",
        "type": "function",
        "z": "78b0f43927df8cf9",
        "name": "S30075",
        "func": "var x = Math.round(msg.payload[0] * 100) / 100;\nflow.set('S30075', x);\nmsg.payload = x + ' kWh';\nreturn msg;",
        "outputs": 1,
        "timeout": 0,
        "noerr": 0,
        "initialize": "",
        "finalize": "",
        "libs": [],
        "x": 1160,
        "y": 2720,
        "wires": [
            []
        ]
    },
    {
        "id": "dd91de7556fbf1cd",
        "type": "delay",
        "z": "78b0f43927df8cf9",
        "name": "",
        "pauseType": "delay",
        "timeout": "5",
        "timeoutUnits": "seconds",
        "rate": "1",
        "nbRateUnits": "1",
        "rateUnits": "second",
        "randomFirst": "1",
        "randomLast": "5",
        "randomUnits": "seconds",
        "drop": false,
        "allowrate": false,
        "outputs": 1,
        "x": 160,
        "y": 940,
        "wires": [
            [
                "c6a08217c11ddb21"
            ]
        ]
    },
    {
        "id": "43c521322db57db6",
        "type": "delay",
        "z": "78b0f43927df8cf9",
        "name": "",
        "pauseType": "delay",
        "timeout": "5",
        "timeoutUnits": "seconds",
        "rate": "1",
        "nbRateUnits": "1",
        "rateUnits": "second",
        "randomFirst": "1",
        "randomLast": "5",
        "randomUnits": "seconds",
        "drop": false,
        "allowrate": false,
        "outputs": 1,
        "x": 220,
        "y": 1180,
        "wires": [
            [
                "7b7087a7f969b323"
            ]
        ]
    },
    {
        "id": "2964726ce5e8a4a8",
        "type": "delay",
        "z": "78b0f43927df8cf9",
        "name": "",
        "pauseType": "delay",
        "timeout": "5",
        "timeoutUnits": "seconds",
        "rate": "1",
        "nbRateUnits": "1",
        "rateUnits": "second",
        "randomFirst": "1",
        "randomLast": "5",
        "randomUnits": "seconds",
        "drop": false,
        "allowrate": false,
        "outputs": 1,
        "x": 160,
        "y": 1540,
        "wires": [
            [
                "e786255b4b63a32d"
            ]
        ]
    },
    {
        "id": "eceb96db23130fed",
        "type": "delay",
        "z": "78b0f43927df8cf9",
        "name": "",
        "pauseType": "delay",
        "timeout": "5",
        "timeoutUnits": "seconds",
        "rate": "1",
        "nbRateUnits": "1",
        "rateUnits": "second",
        "randomFirst": "1",
        "randomLast": "5",
        "randomUnits": "seconds",
        "drop": false,
        "allowrate": false,
        "outputs": 1,
        "x": 220,
        "y": 2040,
        "wires": [
            [
                "33d3f525fd32a651"
            ]
        ]
    },
    {
        "id": "ce20814e5efd9f59",
        "type": "delay",
        "z": "78b0f43927df8cf9",
        "name": "",
        "pauseType": "delay",
        "timeout": "5",
        "timeoutUnits": "seconds",
        "rate": "1",
        "nbRateUnits": "1",
        "rateUnits": "second",
        "randomFirst": "1",
        "randomLast": "5",
        "randomUnits": "seconds",
        "drop": false,
        "allowrate": false,
        "outputs": 1,
        "x": 240,
        "y": 2320,
        "wires": [
            [
                "2cc8cfa8ccce3d07"
            ]
        ]
    },
    {
        "id": "719ba9bd923246ee",
        "type": "delay",
        "z": "78b0f43927df8cf9",
        "name": "",
        "pauseType": "delay",
        "timeout": "5",
        "timeoutUnits": "seconds",
        "rate": "1",
        "nbRateUnits": "1",
        "rateUnits": "second",
        "randomFirst": "1",
        "randomLast": "5",
        "randomUnits": "seconds",
        "drop": false,
        "allowrate": false,
        "outputs": 1,
        "x": 320,
        "y": 2720,
        "wires": [
            [
                "c95f40b16fd869b7"
            ]
        ]
    },
    {
        "id": "34fc306aa3a571c6",
        "type": "inject",
        "z": "78b0f43927df8cf9",
        "name": "Every minute",
        "props": [
            {
                "p": "payload"
            }
        ],
        "repeat": "60",
        "crontab": "",
        "once": false,
        "onceDelay": 0.1,
        "topic": "",
        "payload": "",
        "payloadType": "date",
        "x": 140,
        "y": 860,
        "wires": [
            [
                "dd91de7556fbf1cd"
            ]
        ]
    },
    {
        "id": "420f62f2583cad91",
        "type": "function",
        "z": "78b0f43927df8cf9",
        "name": "S30001",
        "func": "msg.payload = Math.round(msg.payload[0] * 100) / 100\nreturn msg;",
        "outputs": 1,
        "timeout": 0,
        "noerr": 0,
        "initialize": "",
        "finalize": "",
        "libs": [],
        "x": 940,
        "y": 1000,
        "wires": [
            [
                "ef42c2ea35d47344",
                "d23b3642cdf0b1e3"
            ]
        ]
    },
    {
        "id": "38c7c7c266776224",
        "type": "function",
        "z": "78b0f43927df8cf9",
        "name": "S30007",
        "func": "msg.payload = Math.round(msg.payload[0] * 100) / 100;\nreturn msg;",
        "outputs": 1,
        "timeout": 0,
        "noerr": 0,
        "initialize": "",
        "finalize": "",
        "libs": [],
        "x": 940,
        "y": 1240,
        "wires": [
            [
                "671d8fb1b68e57f1",
                "9ec609a331dfb685"
            ]
        ]
    },
    {
        "id": "55cb2e938dc0372e",
        "type": "function",
        "z": "78b0f43927df8cf9",
        "name": "S30013",
        "func": "msg.payload = Math.round(msg.payload[0] * 100) / 100;\nreturn msg;",
        "outputs": 1,
        "timeout": 0,
        "noerr": 0,
        "initialize": "",
        "finalize": "",
        "libs": [],
        "x": 660,
        "y": 1660,
        "wires": [
            [
                "6ad32a4cfe6ed0eb",
                "9e38ad8f8fa13e18"
            ]
        ]
    },
    {
        "id": "b4bc265e559793fe",
        "type": "function",
        "z": "78b0f43927df8cf9",
        "name": "S30071",
        "func": "msg.payload = Math.round(msg.payload[0] * 100) / 100;\nreturn msg;",
        "outputs": 1,
        "timeout": 0,
        "noerr": 0,
        "initialize": "",
        "finalize": "",
        "libs": [],
        "x": 1020,
        "y": 2100,
        "wires": [
            [
                "1cdc75bfaa0bfbe3",
                "e57235f86a17c118"
            ]
        ]
    },
    {
        "id": "111239dcdda15b98",
        "type": "function",
        "z": "78b0f43927df8cf9",
        "name": "S30073",
        "func": "msg.payload = Math.round(msg.payload[0] * 100) / 100;\nreturn msg;",
        "outputs": 1,
        "timeout": 0,
        "noerr": 0,
        "initialize": "",
        "finalize": "",
        "libs": [],
        "x": 1040,
        "y": 2380,
        "wires": [
            [
                "d9bbab7df2117aa0",
                "31faa717432f5bcb"
            ]
        ]
    },
    {
        "id": "74321a5486ef2e12",
        "type": "function",
        "z": "78b0f43927df8cf9",
        "name": "S30075",
        "func": "msg.payload = Math.round(msg.payload[0] * 100) / 100;\nreturn msg;",
        "outputs": 1,
        "timeout": 0,
        "noerr": 0,
        "initialize": "",
        "finalize": "",
        "libs": [],
        "x": 1094.1990966796875,
        "y": 2797.2706298828125,
        "wires": [
            [
                "a18ae3e092087e9c",
                "fef5f83c46a65193"
            ]
        ]
    },
    {
        "id": "ddbd0309105fdd76",
        "type": "buffer-parser",
        "z": "78b0f43927df8cf9",
        "name": "",
        "data": "payload",
        "dataType": "msg",
        "specification": "spec",
        "specificationType": "ui",
        "items": [
            {
                "type": "floatbe",
                "name": "Voltage",
                "offset": 0,
                "length": 1,
                "offsetbit": 0,
                "scale": "1",
                "mask": ""
            }
        ],
        "swap1": "",
        "swap2": "",
        "swap3": "",
        "swap1Type": "swap",
        "swap2Type": "swap",
        "swap3Type": "swap",
        "msgProperty": "payload",
        "msgPropertyType": "str",
        "resultType": "value",
        "resultTypeType": "return",
        "multipleResult": false,
        "fanOutMultipleResult": false,
        "setTopic": true,
        "outputs": 1,
        "x": 710,
        "y": 940,
        "wires": [
            [
                "420f62f2583cad91",
                "6b8159ad83020446"
            ]
        ]
    },
    {
        "id": "577023c58ad2d5da",
        "type": "buffer-parser",
        "z": "78b0f43927df8cf9",
        "name": "",
        "data": "payload",
        "dataType": "msg",
        "specification": "spec",
        "specificationType": "ui",
        "items": [
            {
                "type": "floatbe",
                "name": "Voltage",
                "offset": 0,
                "length": 1,
                "offsetbit": 0,
                "scale": "1",
                "mask": ""
            }
        ],
        "swap1": "",
        "swap2": "",
        "swap3": "",
        "swap1Type": "swap",
        "swap2Type": "swap",
        "swap3Type": "swap",
        "msgProperty": "payload",
        "msgPropertyType": "str",
        "resultType": "value",
        "resultTypeType": "return",
        "multipleResult": false,
        "fanOutMultipleResult": false,
        "setTopic": true,
        "outputs": 1,
        "x": 770,
        "y": 1180,
        "wires": [
            [
                "8bad341de1976d49",
                "38c7c7c266776224"
            ]
        ]
    },
    {
        "id": "4ae7db77ce6da5e8",
        "type": "buffer-parser",
        "z": "78b0f43927df8cf9",
        "name": "",
        "data": "payload",
        "dataType": "msg",
        "specification": "spec",
        "specificationType": "ui",
        "items": [
            {
                "type": "floatbe",
                "name": "Voltage",
                "offset": 0,
                "length": 1,
                "offsetbit": 0,
                "scale": "1",
                "mask": ""
            }
        ],
        "swap1": "",
        "swap2": "",
        "swap3": "",
        "swap1Type": "swap",
        "swap2Type": "swap",
        "swap3Type": "swap",
        "msgProperty": "payload",
        "msgPropertyType": "str",
        "resultType": "value",
        "resultTypeType": "return",
        "multipleResult": false,
        "fanOutMultipleResult": false,
        "setTopic": true,
        "outputs": 1,
        "x": 590,
        "y": 1540,
        "wires": [
            [
                "d50d901d9fb59818",
                "55cb2e938dc0372e"
            ]
        ]
    },
    {
        "id": "ebf9c51e00cae449",
        "type": "buffer-parser",
        "z": "78b0f43927df8cf9",
        "name": "",
        "data": "payload",
        "dataType": "msg",
        "specification": "spec",
        "specificationType": "ui",
        "items": [
            {
                "type": "floatbe",
                "name": "Voltage",
                "offset": 0,
                "length": 1,
                "offsetbit": 0,
                "scale": "1",
                "mask": ""
            }
        ],
        "swap1": "",
        "swap2": "",
        "swap3": "",
        "swap1Type": "swap",
        "swap2Type": "swap",
        "swap3Type": "swap",
        "msgProperty": "payload",
        "msgPropertyType": "str",
        "resultType": "value",
        "resultTypeType": "return",
        "multipleResult": false,
        "fanOutMultipleResult": false,
        "setTopic": true,
        "outputs": 1,
        "x": 850,
        "y": 2320,
        "wires": [
            [
                "8ad6361d59457335",
                "111239dcdda15b98"
            ]
        ]
    },
    {
        "id": "2f822e0156b24531",
        "type": "buffer-parser",
        "z": "78b0f43927df8cf9",
        "name": "",
        "data": "payload",
        "dataType": "msg",
        "specification": "spec",
        "specificationType": "ui",
        "items": [
            {
                "type": "floatbe",
                "name": "ImportActiveEnergy ",
                "offset": 0,
                "length": 1,
                "offsetbit": 0,
                "scale": "1",
                "mask": ""
            }
        ],
        "swap1": "",
        "swap2": "",
        "swap3": "",
        "swap1Type": "swap",
        "swap2Type": "swap",
        "swap3Type": "swap",
        "msgProperty": "payload",
        "msgPropertyType": "str",
        "resultType": "value",
        "resultTypeType": "return",
        "multipleResult": false,
        "fanOutMultipleResult": false,
        "setTopic": true,
        "outputs": 1,
        "x": 830,
        "y": 2040,
        "wires": [
            [
                "881bf1ad6264efb3",
                "b4bc265e559793fe"
            ]
        ]
    },
    {
        "id": "325b6a91d0c138bc",
        "type": "buffer-parser",
        "z": "78b0f43927df8cf9",
        "name": "",
        "data": "payload",
        "dataType": "msg",
        "specification": "spec",
        "specificationType": "ui",
        "items": [
            {
                "type": "floatbe",
                "name": "Voltage",
                "offset": 0,
                "length": 1,
                "offsetbit": 0,
                "scale": "1",
                "mask": ""
            }
        ],
        "swap1": "",
        "swap2": "",
        "swap3": "",
        "swap1Type": "swap",
        "swap2Type": "swap",
        "swap3Type": "swap",
        "msgProperty": "payload",
        "msgPropertyType": "str",
        "resultType": "value",
        "resultTypeType": "return",
        "multipleResult": false,
        "fanOutMultipleResult": false,
        "setTopic": true,
        "outputs": 1,
        "x": 890,
        "y": 2720,
        "wires": [
            [
                "d8df70aa3f514bf9",
                "74321a5486ef2e12"
            ]
        ]
    },
    {
        "id": "c6a08217c11ddb21",
        "type": "modbus-getter",
        "z": "78b0f43927df8cf9",
        "name": "30001 Phase 1 line to neutral volts.",
        "showStatusActivities": true,
        "showErrors": true,
        "showWarnings": true,
        "logIOActivities": false,
        "unitid": "1",
        "dataType": "InputRegister",
        "adr": "0",
        "quantity": "2",
        "server": "91059c5b0441c792",
        "useIOFile": false,
        "ioFile": "",
        "useIOForPayload": false,
        "emptyMsgOnFail": true,
        "keepMsgProperties": true,
        "delayOnStart": false,
        "enableDeformedMessages": false,
        "startDelayTime": "",
        "x": 460,
        "y": 940,
        "wires": [
            [
                "ddbd0309105fdd76"
            ],
            [
                "43c521322db57db6"
            ]
        ]
    },
    {
        "id": "7b7087a7f969b323",
        "type": "modbus-getter",
        "z": "78b0f43927df8cf9",
        "name": "30007 Current",
        "showStatusActivities": true,
        "showErrors": true,
        "showWarnings": true,
        "logIOActivities": false,
        "unitid": "1",
        "dataType": "InputRegister",
        "adr": "6",
        "quantity": "2",
        "server": "91059c5b0441c792",
        "useIOFile": false,
        "ioFile": "",
        "useIOForPayload": false,
        "emptyMsgOnFail": true,
        "keepMsgProperties": true,
        "delayOnStart": false,
        "enableDeformedMessages": false,
        "startDelayTime": "",
        "x": 460,
        "y": 1180,
        "wires": [
            [
                "577023c58ad2d5da"
            ],
            [
                "2964726ce5e8a4a8"
            ]
        ]
    },
    {
        "id": "e786255b4b63a32d",
        "type": "modbus-getter",
        "z": "78b0f43927df8cf9",
        "name": "30013 Active power",
        "showStatusActivities": true,
        "showErrors": true,
        "showWarnings": true,
        "logIOActivities": false,
        "unitid": "1",
        "dataType": "InputRegister",
        "adr": "12",
        "quantity": "2",
        "server": "91059c5b0441c792",
        "useIOFile": false,
        "ioFile": "",
        "useIOForPayload": false,
        "emptyMsgOnFail": true,
        "keepMsgProperties": true,
        "delayOnStart": false,
        "enableDeformedMessages": false,
        "startDelayTime": "",
        "x": 370,
        "y": 1540,
        "wires": [
            [
                "4ae7db77ce6da5e8"
            ],
            [
                "eceb96db23130fed"
            ]
        ]
    },
    {
        "id": "2cc8cfa8ccce3d07",
        "type": "modbus-getter",
        "z": "78b0f43927df8cf9",
        "name": "30073 Import active energy",
        "showStatusActivities": true,
        "showErrors": true,
        "showWarnings": true,
        "logIOActivities": false,
        "unitid": "1",
        "dataType": "InputRegister",
        "adr": "72",
        "quantity": "2",
        "server": "91059c5b0441c792",
        "useIOFile": false,
        "ioFile": "",
        "useIOForPayload": false,
        "emptyMsgOnFail": true,
        "keepMsgProperties": true,
        "delayOnStart": false,
        "enableDeformedMessages": false,
        "startDelayTime": "",
        "x": 580,
        "y": 2320,
        "wires": [
            [
                "ebf9c51e00cae449"
            ],
            [
                "719ba9bd923246ee"
            ]
        ]
    },
    {
        "id": "33d3f525fd32a651",
        "type": "modbus-getter",
        "z": "78b0f43927df8cf9",
        "name": "30071 Frequency of supply voltages.",
        "showStatusActivities": true,
        "showErrors": true,
        "showWarnings": true,
        "logIOActivities": false,
        "unitid": "1",
        "dataType": "InputRegister",
        "adr": "70",
        "quantity": "2",
        "server": "91059c5b0441c792",
        "useIOFile": false,
        "ioFile": "",
        "useIOForPayload": false,
        "emptyMsgOnFail": true,
        "keepMsgProperties": true,
        "delayOnStart": false,
        "enableDeformedMessages": false,
        "startDelayTime": "",
        "x": 550,
        "y": 2040,
        "wires": [
            [
                "2f822e0156b24531"
            ],
            [
                "ce20814e5efd9f59"
            ]
        ]
    },
    {
        "id": "c95f40b16fd869b7",
        "type": "modbus-getter",
        "z": "78b0f43927df8cf9",
        "name": "30075 Export active energy",
        "showStatusActivities": true,
        "showErrors": true,
        "showWarnings": true,
        "logIOActivities": false,
        "unitid": "1",
        "dataType": "InputRegister",
        "adr": "74",
        "quantity": "2",
        "server": "91059c5b0441c792",
        "useIOFile": false,
        "ioFile": "",
        "useIOForPayload": false,
        "emptyMsgOnFail": true,
        "keepMsgProperties": true,
        "delayOnStart": false,
        "enableDeformedMessages": false,
        "startDelayTime": "",
        "x": 620,
        "y": 2720,
        "wires": [
            [
                "325b6a91d0c138bc"
            ],
            []
        ]
    },
    {
        "id": "7c180442be53fa33",
        "type": "ui_text",
        "z": "78b0f43927df8cf9",
        "group": "936f51254fd84fc9",
        "order": 2,
        "width": 0,
        "height": 0,
        "name": "",
        "label": "Voltage",
        "format": "{{msg.payload}}",
        "layout": "row-spread",
        "className": "",
        "style": false,
        "font": "",
        "fontSize": "",
        "color": "#000000",
        "x": 1260,
        "y": 940,
        "wires": []
    },
    {
        "id": "2672bc5185574ca9",
        "type": "ui_text",
        "z": "78b0f43927df8cf9",
        "group": "936f51254fd84fc9",
        "order": 3,
        "width": 0,
        "height": 0,
        "name": "",
        "label": "Current",
        "format": "{{msg.payload}}",
        "layout": "row-spread",
        "className": "",
        "style": false,
        "font": "",
        "fontSize": "",
        "color": "#000000",
        "x": 1320,
        "y": 1180,
        "wires": []
    },
    {
        "id": "d481cbd4d0e9a444",
        "type": "ui_text",
        "z": "78b0f43927df8cf9",
        "group": "936f51254fd84fc9",
        "order": 4,
        "width": 0,
        "height": 0,
        "name": "",
        "label": "Active Pover",
        "format": "{{msg.payload}}",
        "layout": "row-spread",
        "className": "",
        "style": false,
        "font": "",
        "fontSize": "",
        "color": "#000000",
        "x": 1170,
        "y": 1540,
        "wires": []
    },
    {
        "id": "f2db9c1245079aa9",
        "type": "ui_text",
        "z": "78b0f43927df8cf9",
        "group": "936f51254fd84fc9",
        "order": 5,
        "width": 0,
        "height": 0,
        "name": "",
        "label": "Import Energie",
        "format": "{{msg.payload}}",
        "layout": "row-spread",
        "className": "",
        "style": false,
        "font": "",
        "fontSize": "",
        "color": "#000000",
        "x": 1380,
        "y": 2320,
        "wires": []
    },
    {
        "id": "5c1e9f865fa36127",
        "type": "ui_text",
        "z": "78b0f43927df8cf9",
        "group": "936f51254fd84fc9",
        "order": 1,
        "width": 0,
        "height": 0,
        "name": "",
        "label": "Frequency",
        "format": "{{msg.payload}}",
        "layout": "row-spread",
        "className": "",
        "style": false,
        "font": "",
        "fontSize": "",
        "color": "#000000",
        "x": 1370.1990966796875,
        "y": 2040.1416015625,
        "wires": []
    },
    {
        "id": "ef42c2ea35d47344",
        "type": "rbe",
        "z": "78b0f43927df8cf9",
        "name": "Block until the value change is greater than 1",
        "func": "deadband",
        "gap": "1",
        "start": "",
        "inout": "out",
        "septopics": false,
        "property": "payload",
        "topi": "topic",
        "x": 750,
        "y": 1080,
        "wires": [
            [
                "5a760bd0b48cdc42"
            ]
        ]
    },
    {
        "id": "eb02d09b3d52cc88",
        "type": "GSheet",
        "z": "78b0f43927df8cf9",
        "creds": "1c71a74439a03faa",
        "method": "update",
        "action": "",
        "sheet": "",
        "cells": "solar!F4",
        "flatten": true,
        "name": "solar!F4",
        "x": 1280,
        "y": 1080,
        "wires": [
            []
        ]
    },
    {
        "id": "5a760bd0b48cdc42",
        "type": "function",
        "z": "78b0f43927df8cf9",
        "name": "S30001",
        "func": "msg.payload = Math.round(flow.get('S30001'));\nreturn msg;",
        "outputs": 1,
        "timeout": 0,
        "noerr": 0,
        "initialize": "",
        "finalize": "",
        "libs": [],
        "x": 1060,
        "y": 1080,
        "wires": [
            [
                "eb02d09b3d52cc88"
            ]
        ]
    },
    {
        "id": "d480f8f0e1484ac9",
        "type": "inject",
        "z": "78b0f43927df8cf9",
        "name": "Once after 90s",
        "props": [
            {
                "p": "payload"
            }
        ],
        "repeat": "",
        "crontab": "",
        "once": true,
        "onceDelay": "90",
        "topic": "",
        "payload": "true",
        "payloadType": "bool",
        "x": 780,
        "y": 1120,
        "wires": [
            [
                "5a760bd0b48cdc42"
            ]
        ]
    },
    {
        "id": "671d8fb1b68e57f1",
        "type": "rbe",
        "z": "78b0f43927df8cf9",
        "name": "Block until the value change is greater than 0.1",
        "func": "deadband",
        "gap": "0.1",
        "start": "",
        "inout": "out",
        "septopics": false,
        "property": "payload",
        "topi": "topic",
        "x": 740,
        "y": 1400,
        "wires": [
            [
                "8c4268c12b2b4e23"
            ]
        ]
    },
    {
        "id": "8c4268c12b2b4e23",
        "type": "function",
        "z": "78b0f43927df8cf9",
        "name": "S30007",
        "func": "msg.payload = Math.round(flow.get('S30007'));\nreturn msg;",
        "outputs": 1,
        "timeout": 0,
        "noerr": 0,
        "initialize": "",
        "finalize": "",
        "libs": [],
        "x": 1080,
        "y": 1400,
        "wires": [
            [
                "1af69193f1c5a874"
            ]
        ]
    },
    {
        "id": "8a354c5442868e8e",
        "type": "inject",
        "z": "78b0f43927df8cf9",
        "name": "Once after 90s",
        "props": [
            {
                "p": "payload"
            }
        ],
        "repeat": "",
        "crontab": "",
        "once": true,
        "onceDelay": "90",
        "topic": "",
        "payload": "true",
        "payloadType": "bool",
        "x": 880,
        "y": 1460,
        "wires": [
            [
                "8c4268c12b2b4e23"
            ]
        ]
    },
    {
        "id": "6ad32a4cfe6ed0eb",
        "type": "rbe",
        "z": "78b0f43927df8cf9",
        "name": "Block until the value change is greater than 1",
        "func": "deadband",
        "gap": "1",
        "start": "",
        "inout": "out",
        "septopics": false,
        "property": "payload",
        "topi": "topic",
        "x": 790,
        "y": 1760,
        "wires": [
            [
                "b2d272e2bd3a0a8a"
            ]
        ]
    },
    {
        "id": "52c39cfad2e34392",
        "type": "GSheet",
        "z": "78b0f43927df8cf9",
        "creds": "1c71a74439a03faa",
        "method": "update",
        "action": "",
        "sheet": "",
        "cells": "solar!F6",
        "flatten": true,
        "name": "solar!F6",
        "x": 1300,
        "y": 1760,
        "wires": [
            []
        ]
    },
    {
        "id": "b2d272e2bd3a0a8a",
        "type": "function",
        "z": "78b0f43927df8cf9",
        "name": "S30013",
        "func": "msg.payload = Math.round(flow.get('S30013'));\nreturn msg;",
        "outputs": 1,
        "timeout": 0,
        "noerr": 0,
        "initialize": "",
        "finalize": "",
        "libs": [],
        "x": 1080,
        "y": 1760,
        "wires": [
            [
                "52c39cfad2e34392",
                "e3998d6231748919",
                "17ca27f0ca7eb917",
                "e7cd039873506b49"
            ]
        ]
    },
    {
        "id": "cd7f6ac4fb1a0d35",
        "type": "inject",
        "z": "78b0f43927df8cf9",
        "name": "Once after 90s",
        "props": [
            {
                "p": "payload"
            }
        ],
        "repeat": "",
        "crontab": "",
        "once": true,
        "onceDelay": "90",
        "topic": "",
        "payload": "true",
        "payloadType": "bool",
        "x": 840,
        "y": 1820,
        "wires": [
            [
                "b2d272e2bd3a0a8a"
            ]
        ]
    },
    {
        "id": "1cdc75bfaa0bfbe3",
        "type": "rbe",
        "z": "78b0f43927df8cf9",
        "name": "Block until the value change is greater than 1",
        "func": "deadband",
        "gap": "1",
        "start": "",
        "inout": "out",
        "septopics": false,
        "property": "payload",
        "topi": "topic",
        "x": 930,
        "y": 2180,
        "wires": [
            [
                "9121b71782d5f242"
            ]
        ]
    },
    {
        "id": "0afbee3935a06d7d",
        "type": "GSheet",
        "z": "78b0f43927df8cf9",
        "creds": "1c71a74439a03faa",
        "method": "update",
        "action": "",
        "sheet": "",
        "cells": "solar!F7",
        "flatten": true,
        "name": "solar!F7",
        "x": 1420,
        "y": 2200,
        "wires": [
            []
        ]
    },
    {
        "id": "9121b71782d5f242",
        "type": "function",
        "z": "78b0f43927df8cf9",
        "name": "S30071",
        "func": "msg.payload = Math.round(flow.get('S30071'));\nreturn msg;",
        "outputs": 1,
        "timeout": 0,
        "noerr": 0,
        "initialize": "",
        "finalize": "",
        "libs": [],
        "x": 1200,
        "y": 2200,
        "wires": [
            [
                "0afbee3935a06d7d"
            ]
        ]
    },
    {
        "id": "81da58d680d0c5df",
        "type": "inject",
        "z": "78b0f43927df8cf9",
        "name": "Once after 90s",
        "props": [
            {
                "p": "payload"
            }
        ],
        "repeat": "",
        "crontab": "",
        "once": true,
        "onceDelay": "90",
        "topic": "",
        "payload": "true",
        "payloadType": "bool",
        "x": 1000,
        "y": 2260,
        "wires": [
            [
                "9121b71782d5f242"
            ]
        ]
    },
    {
        "id": "d9bbab7df2117aa0",
        "type": "rbe",
        "z": "78b0f43927df8cf9",
        "name": "Block until the value change is greater than 1",
        "func": "deadband",
        "gap": "1",
        "start": "",
        "inout": "out",
        "septopics": false,
        "property": "payload",
        "topi": "topic",
        "x": 990,
        "y": 2580,
        "wires": [
            [
                "2f670b620801b7ab"
            ]
        ]
    },
    {
        "id": "f40d11091d3f04d1",
        "type": "GSheet",
        "z": "78b0f43927df8cf9",
        "creds": "1c71a74439a03faa",
        "method": "update",
        "action": "",
        "sheet": "",
        "cells": "solar!F8",
        "flatten": true,
        "name": "solar!F8",
        "x": 1460,
        "y": 2580,
        "wires": [
            []
        ]
    },
    {
        "id": "2f670b620801b7ab",
        "type": "function",
        "z": "78b0f43927df8cf9",
        "name": "S30073",
        "func": "msg.payload = Math.round(flow.get('S30073'));\nreturn msg;",
        "outputs": 1,
        "timeout": 0,
        "noerr": 0,
        "initialize": "",
        "finalize": "",
        "libs": [],
        "x": 1240,
        "y": 2580,
        "wires": [
            [
                "f40d11091d3f04d1"
            ]
        ]
    },
    {
        "id": "8fc20b2344571714",
        "type": "inject",
        "z": "78b0f43927df8cf9",
        "name": "Once after 90s",
        "props": [
            {
                "p": "payload"
            }
        ],
        "repeat": "",
        "crontab": "",
        "once": true,
        "onceDelay": "90",
        "topic": "",
        "payload": "true",
        "payloadType": "bool",
        "x": 1040,
        "y": 2640,
        "wires": [
            [
                "2f670b620801b7ab"
            ]
        ]
    },
    {
        "id": "a18ae3e092087e9c",
        "type": "rbe",
        "z": "78b0f43927df8cf9",
        "name": "Block until the value change is greater than 1",
        "func": "deadband",
        "gap": "1",
        "start": "",
        "inout": "out",
        "septopics": false,
        "property": "payload",
        "topi": "topic",
        "x": 970,
        "y": 2940,
        "wires": [
            [
                "f38f235171dead3f"
            ]
        ]
    },
    {
        "id": "de3938dce8916954",
        "type": "GSheet",
        "z": "78b0f43927df8cf9",
        "creds": "1c71a74439a03faa",
        "method": "update",
        "action": "",
        "sheet": "",
        "cells": "solar!F9",
        "flatten": true,
        "name": "solar!F9",
        "x": 1440,
        "y": 2940,
        "wires": [
            []
        ]
    },
    {
        "id": "f38f235171dead3f",
        "type": "function",
        "z": "78b0f43927df8cf9",
        "name": "S30075",
        "func": "msg.payload = Math.round(flow.get('S30075'));\nreturn msg;",
        "outputs": 1,
        "timeout": 0,
        "noerr": 0,
        "initialize": "",
        "finalize": "",
        "libs": [],
        "x": 1220,
        "y": 2940,
        "wires": [
            [
                "de3938dce8916954"
            ]
        ]
    },
    {
        "id": "456750ab7182f916",
        "type": "inject",
        "z": "78b0f43927df8cf9",
        "name": "Once after 90s",
        "props": [
            {
                "p": "payload"
            }
        ],
        "repeat": "",
        "crontab": "",
        "once": true,
        "onceDelay": "90",
        "topic": "",
        "payload": "true",
        "payloadType": "bool",
        "x": 1020,
        "y": 3000,
        "wires": [
            [
                "f38f235171dead3f"
            ]
        ]
    },
    {
        "id": "d23b3642cdf0b1e3",
        "type": "mqtt out",
        "z": "78b0f43927df8cf9",
        "name": "SolarMeterCloud/Solar/Meter/VoltageS30001",
        "topic": "SolarMeterCloud/Solar/Meter/VoltageS30001",
        "qos": "0",
        "retain": "",
        "respTopic": "",
        "contentType": "",
        "userProps": "",
        "correl": "",
        "expiry": "",
        "broker": "7edadfdc191a40bf",
        "x": 1250,
        "y": 1000,
        "wires": []
    },
    {
        "id": "9ec609a331dfb685",
        "type": "mqtt out",
        "z": "78b0f43927df8cf9",
        "name": "SolarMeterCloud/Solar/Meter/CurrentS30007",
        "topic": "SolarMeterCloud/Solar/Meter/CurrentS30007",
        "qos": "0",
        "retain": "",
        "respTopic": "",
        "contentType": "",
        "userProps": "",
        "correl": "",
        "expiry": "",
        "broker": "7edadfdc191a40bf",
        "x": 1250,
        "y": 1280,
        "wires": []
    },
    {
        "id": "9e38ad8f8fa13e18",
        "type": "mqtt out",
        "z": "78b0f43927df8cf9",
        "name": "SolarMeterCloud/Solar/Meter/ActivePowerS30013",
        "topic": "SolarMeterCloud/Solar/Meter/ActivePowerS30013",
        "qos": "0",
        "retain": "",
        "respTopic": "",
        "contentType": "",
        "userProps": "",
        "correl": "",
        "expiry": "",
        "broker": "7edadfdc191a40bf",
        "x": 970,
        "y": 1660,
        "wires": []
    },
    {
        "id": "e57235f86a17c118",
        "type": "mqtt out",
        "z": "78b0f43927df8cf9",
        "name": "SolarMeterCloud/Solar/Meter/FrequencyS30071",
        "topic": "SolarMeterCloud/Solar/Meter/FrequencyS30071",
        "qos": "0",
        "retain": "",
        "respTopic": "",
        "contentType": "",
        "userProps": "",
        "correl": "",
        "expiry": "",
        "broker": "7edadfdc191a40bf",
        "x": 1310.1990966796875,
        "y": 2157.2060546875,
        "wires": []
    },
    {
        "id": "31faa717432f5bcb",
        "type": "mqtt out",
        "z": "78b0f43927df8cf9",
        "name": "SolarMeterCloud/Solar/Meter/ImportEnergyS30073",
        "topic": "SolarMeterCloud/Solar/Meter/ImportEnergyS30073",
        "qos": "0",
        "retain": "",
        "respTopic": "",
        "contentType": "",
        "userProps": "",
        "correl": "",
        "expiry": "",
        "broker": "7edadfdc191a40bf",
        "x": 1370,
        "y": 2460,
        "wires": []
    },
    {
        "id": "fef5f83c46a65193",
        "type": "mqtt out",
        "z": "78b0f43927df8cf9",
        "name": "SolarMeterCloud/Solar/Meter/ExportEnergyS30075",
        "topic": "SolarMeterCloud/Solar/Meter/ExportEnergyS30075",
        "qos": "0",
        "retain": "",
        "respTopic": "",
        "contentType": "",
        "userProps": "",
        "correl": "",
        "expiry": "",
        "broker": "7edadfdc191a40bf",
        "x": 1430,
        "y": 2800,
        "wires": []
    },
    {
        "id": "a94e53cf6821a2af",
        "type": "function",
        "z": "78b0f43927df8cf9",
        "name": "Sheet1!A4:G4",
        "func": "msg.payload = [flow.get('timestamp'),flow.get('S30013Average1day'), flow.get('S30013Minimum1day'), flow.get('S30013Maximum1day')\n, flow.get('S30073'), flow.get('S30075'),];\nreturn msg;",
        "outputs": 1,
        "timeout": 0,
        "noerr": 0,
        "initialize": "",
        "finalize": "",
        "libs": [],
        "x": 560,
        "y": 3160,
        "wires": [
            [
                "76b917ab51814f02"
            ]
        ]
    },
    {
        "id": "76b917ab51814f02",
        "type": "GSheet",
        "z": "78b0f43927df8cf9",
        "creds": "1c71a74439a03faa",
        "method": "append",
        "action": "",
        "sheet": "",
        "cells": "solarStatistics!A4:G4",
        "flatten": true,
        "name": "solarStatistics!A4:G4",
        "x": 780,
        "y": 3160,
        "wires": [
            []
        ]
    },
    {
        "id": "484f2c3cfa53c147",
        "type": "inject",
        "z": "78b0f43927df8cf9",
        "name": "every day at 02:00 o' clock",
        "props": [
            {
                "p": "payload"
            },
            {
                "p": "topic",
                "vt": "str"
            }
        ],
        "repeat": "",
        "crontab": "00 02 * * *",
        "once": false,
        "onceDelay": 0.1,
        "topic": "",
        "payload": "",
        "payloadType": "date",
        "x": 300,
        "y": 3160,
        "wires": [
            [
                "a94e53cf6821a2af"
            ]
        ]
    },
    {
        "id": "861c690d440a0207",
        "type": "comment",
        "z": "78b0f43927df8cf9",
        "name": "present value",
        "info": "",
        "x": 1450,
        "y": 2980,
        "wires": []
    },
    {
        "id": "40cd998426cb9d94",
        "type": "comment",
        "z": "78b0f43927df8cf9",
        "name": "present value",
        "info": "",
        "x": 1470,
        "y": 2620,
        "wires": []
    },
    {
        "id": "381dbee28404a6db",
        "type": "comment",
        "z": "78b0f43927df8cf9",
        "name": "present value",
        "info": "",
        "x": 1410,
        "y": 2240,
        "wires": []
    },
    {
        "id": "0aa1ce147549586b",
        "type": "comment",
        "z": "78b0f43927df8cf9",
        "name": "present value",
        "info": "",
        "x": 1370,
        "y": 2080,
        "wires": []
    },
    {
        "id": "07831dbda73430d3",
        "type": "comment",
        "z": "78b0f43927df8cf9",
        "name": "present value",
        "info": "",
        "x": 1310,
        "y": 1440,
        "wires": []
    },
    {
        "id": "d4637a07c833a336",
        "type": "comment",
        "z": "78b0f43927df8cf9",
        "name": "present value",
        "info": "",
        "x": 1291.1990966796875,
        "y": 1118.1416015625,
        "wires": []
    },
    {
        "id": "60f9d3e49146e697",
        "type": "function",
        "z": "78b0f43927df8cf9",
        "name": "S30013Average1day",
        "func": "flow.set('S30013Average1day', msg.payload);\nreturn msg;",
        "outputs": 1,
        "timeout": 0,
        "noerr": 0,
        "initialize": "",
        "finalize": "",
        "libs": [],
        "x": 1500,
        "y": 1860,
        "wires": [
            []
        ]
    },
    {
        "id": "e9bf4735789b4534",
        "type": "function",
        "z": "78b0f43927df8cf9",
        "name": "S30013Minimum1day",
        "func": "flow.set('S30013Minimum1day', msg.payload);\nreturn msg;",
        "outputs": 1,
        "timeout": 0,
        "noerr": 0,
        "initialize": "",
        "finalize": "",
        "libs": [],
        "x": 1500,
        "y": 1900,
        "wires": [
            []
        ]
    },
    {
        "id": "ea0c825cad972fa7",
        "type": "function",
        "z": "78b0f43927df8cf9",
        "name": "S30013Maximum1day",
        "func": "flow.set('S30013Maximum1day', msg.payload);\nreturn msg;",
        "outputs": 1,
        "timeout": 0,
        "noerr": 0,
        "initialize": "",
        "finalize": "",
        "libs": [],
        "x": 1500,
        "y": 1940,
        "wires": [
            []
        ]
    },
    {
        "id": "a9ca21c8c1a6dcaa",
        "type": "comment",
        "z": "78b0f43927df8cf9",
        "name": "present value",
        "info": "",
        "x": 1310,
        "y": 1800,
        "wires": []
    },
    {
        "id": "a9fdca1c33b88176",
        "type": "comment",
        "z": "78b0f43927df8cf9",
        "name": "solar statistics fully available",
        "info": "",
        "x": 780,
        "y": 3200,
        "wires": []
    },
    {
        "id": "e3998d6231748919",
        "type": "aggregator",
        "z": "78b0f43927df8cf9",
        "name": "S30013Average1day",
        "topic": "",
        "intervalCount": "1",
        "intervalUnits": "d",
        "submitIncompleteInterval": false,
        "submitPerTopic": false,
        "aggregationType": "mean",
        "x": 1260,
        "y": 1860,
        "wires": [
            [
                "60f9d3e49146e697"
            ]
        ]
    },
    {
        "id": "17ca27f0ca7eb917",
        "type": "aggregator",
        "z": "78b0f43927df8cf9",
        "name": "S30013Minimum1day",
        "topic": "",
        "intervalCount": "1",
        "intervalUnits": "d",
        "submitIncompleteInterval": false,
        "submitPerTopic": false,
        "aggregationType": "min",
        "x": 1260,
        "y": 1900,
        "wires": [
            [
                "e9bf4735789b4534"
            ]
        ]
    },
    {
        "id": "e7cd039873506b49",
        "type": "aggregator",
        "z": "78b0f43927df8cf9",
        "name": "S30013Maximum1day",
        "topic": "",
        "intervalCount": "1",
        "intervalUnits": "d",
        "submitIncompleteInterval": false,
        "submitPerTopic": false,
        "aggregationType": "max",
        "x": 1260,
        "y": 1940,
        "wires": [
            [
                "ea0c825cad972fa7"
            ]
        ]
    },
    {
        "id": "2adbd67c4683f59b",
        "type": "inject",
        "z": "78b0f43927df8cf9",
        "name": "intervall 1 sec",
        "props": [
            {
                "p": "payload"
            },
            {
                "p": "topic",
                "vt": "str"
            }
        ],
        "repeat": "1",
        "crontab": "",
        "once": true,
        "onceDelay": 0.1,
        "topic": "",
        "payload": "",
        "payloadType": "date",
        "x": 360,
        "y": 700,
        "wires": [
            [
                "4a1fbed4b3770578"
            ]
        ]
    },
    {
        "id": "4a1fbed4b3770578",
        "type": "function",
        "z": "78b0f43927df8cf9",
        "name": "timestamp",
        "func": "global.set('timestamp', new Date().toISOString() ); \nnew Date(1777139513587).toISOString()\n// Generate an ISO‑8601 timestamp in UTC (English, international, unambiguous)\nmsg.payload = new Date().toISOString();\nflow.set('timestamp', msg.payload);\nreturn msg;",
        "outputs": 1,
        "timeout": "",
        "noerr": 0,
        "initialize": "",
        "finalize": "",
        "libs": [],
        "x": 710,
        "y": 700,
        "wires": [
            [
                "7e209d733d492bae"
            ]
        ]
    },
    {
        "id": "7e209d733d492bae",
        "type": "ui_text",
        "z": "78b0f43927df8cf9",
        "group": "85f3ae867011b7a8",
        "order": 2,
        "width": 0,
        "height": 0,
        "name": "Timestamp",
        "label": "Timestamp",
        "format": "{{msg.payload}}",
        "layout": "row-spread",
        "className": "",
        "style": false,
        "font": "",
        "fontSize": "",
        "color": "#000000",
        "x": 930,
        "y": 700,
        "wires": []
    },
    {
        "id": "1af69193f1c5a874",
        "type": "GSheet",
        "z": "78b0f43927df8cf9",
        "creds": "1c71a74439a03faa",
        "method": "update",
        "action": "",
        "sheet": "",
        "cells": "solar!F5",
        "flatten": true,
        "name": "solar!F5",
        "x": 1300,
        "y": 1400,
        "wires": [
            []
        ]
    },
    {
        "id": "43d065da5293cc4e",
        "type": "comment",
        "z": "78b0f43927df8cf9",
        "name": "solar statistics rolling 30‑day period ",
        "info": "",
        "x": 300,
        "y": 3300,
        "wires": []
    },
    {
        "id": "3d428d23b4907d11",
        "type": "function",
        "z": "78b0f43927df8cf9",
        "name": "solarRolling!A33:F33",
        "func": "msg.payload = [flow.get('timestamp'),flow.get('S30013Average1day'), flow.get('S30013Minimum1day'), flow.get('S30013Maximum1day')\n, flow.get('S30073'), flow.get('S30075'),];\nreturn msg;",
        "outputs": 1,
        "timeout": 0,
        "noerr": 0,
        "initialize": "",
        "finalize": "",
        "libs": [],
        "x": 860,
        "y": 3600,
        "wires": [
            [
                "9c0f2a60d5113972"
            ]
        ]
    },
    {
        "id": "bcb6c0820d8d6214",
        "type": "comment",
        "z": "78b0f43927df8cf9",
        "name": "update cells",
        "info": "",
        "x": 150,
        "y": 3560,
        "wires": []
    },
    {
        "id": "be4877029760f382",
        "type": "comment",
        "z": "78b0f43927df8cf9",
        "name": "Get Row",
        "info": "",
        "x": 860,
        "y": 3360,
        "wires": []
    },
    {
        "id": "62bf70c920678746",
        "type": "GSheet",
        "z": "78b0f43927df8cf9",
        "creds": "1c71a74439a03faa",
        "method": "update",
        "action": "",
        "sheet": "",
        "cells": "solarRolling!A4:F32",
        "flatten": false,
        "name": "solarRolling!A4:F32",
        "x": 150,
        "y": 3600,
        "wires": [
            [
                "9335bf2081343b9a"
            ]
        ]
    },
    {
        "id": "8866c3ee6f7ce2c4",
        "type": "GSheet",
        "z": "78b0f43927df8cf9",
        "creds": "1c71a74439a03faa",
        "method": "get",
        "action": "",
        "sheet": "",
        "cells": "solarRolling!A5:F33",
        "flatten": false,
        "name": "solarRolling!A5:F33",
        "x": 870,
        "y": 3400,
        "wires": [
            [
                "998fb99750c29f0f"
            ]
        ]
    },
    {
        "id": "998fb99750c29f0f",
        "type": "delay",
        "z": "78b0f43927df8cf9",
        "name": "",
        "pauseType": "delay",
        "timeout": "30",
        "timeoutUnits": "seconds",
        "rate": "1",
        "nbRateUnits": "1",
        "rateUnits": "second",
        "randomFirst": "1",
        "randomLast": "5",
        "randomUnits": "seconds",
        "drop": false,
        "allowrate": false,
        "outputs": 1,
        "x": 1170,
        "y": 3400,
        "wires": [
            [
                "62bf70c920678746"
            ]
        ]
    },
    {
        "id": "9335bf2081343b9a",
        "type": "delay",
        "z": "78b0f43927df8cf9",
        "name": "",
        "pauseType": "delay",
        "timeout": "30",
        "timeoutUnits": "seconds",
        "rate": "1",
        "nbRateUnits": "1",
        "rateUnits": "second",
        "randomFirst": "1",
        "randomLast": "5",
        "randomUnits": "seconds",
        "drop": false,
        "allowrate": false,
        "outputs": 1,
        "x": 530,
        "y": 3600,
        "wires": [
            [
                "3d428d23b4907d11"
            ]
        ]
    },
    {
        "id": "9c0f2a60d5113972",
        "type": "GSheet",
        "z": "78b0f43927df8cf9",
        "creds": "1c71a74439a03faa",
        "method": "update",
        "action": "",
        "sheet": "",
        "cells": "solarRolling!A33:F33",
        "flatten": true,
        "name": "solarRolling!A33:F33",
        "x": 1160,
        "y": 3600,
        "wires": [
            []
        ]
    },
    {
        "id": "977d3a3607f2dc2d",
        "type": "comment",
        "z": "78b0f43927df8cf9",
        "name": "Update Cells",
        "info": "",
        "x": 1130,
        "y": 3560,
        "wires": []
    },
    {
        "id": "c9407f7cf7d0241f",
        "type": "inject",
        "z": "78b0f43927df8cf9",
        "name": "every day at 03:00 o' clock",
        "props": [
            {
                "p": "payload"
            }
        ],
        "repeat": "",
        "crontab": "00 03 * * *",
        "once": false,
        "onceDelay": 0.1,
        "topic": "",
        "payload": "",
        "payloadType": "date",
        "x": 200,
        "y": 3400,
        "wires": [
            [
                "8866c3ee6f7ce2c4"
            ]
        ]
    },
    {
        "id": "91059c5b0441c792",
        "type": "modbus-client",
        "name": "Solarstrom",
        "clienttype": "serial",
        "bufferCommands": true,
        "stateLogEnabled": false,
        "queueLogEnabled": false,
        "failureLogEnabled": true,
        "tcpHost": "127.0.0.1",
        "tcpPort": "502",
        "tcpType": "DEFAULT",
        "serialPort": "/dev/ttyACM0",
        "serialType": "RTU-BUFFERD",
        "serialBaudrate": "19200",
        "serialDatabits": "8",
        "serialStopbits": "1",
        "serialParity": "none",
        "serialConnectionDelay": "1000",
        "serialAsciiResponseStartDelimiter": "0x3A",
        "unit_id": "20",
        "commandDelay": "1",
        "clientTimeout": "1000",
        "reconnectOnTimeout": true,
        "reconnectTimeout": "2000",
        "parallelUnitIdsAllowed": true,
        "showErrors": false,
        "showWarnings": true,
        "showLogs": true
    },
    {
        "id": "936f51254fd84fc9",
        "type": "ui_group",
        "name": "Solar",
        "tab": "f28bfc920b47689d",
        "order": 2,
        "disp": true,
        "width": "6",
        "collapse": false,
        "className": ""
    },
    {
        "id": "1c71a74439a03faa",
        "type": "gauth",
        "name": "Unknown"
    },
    {
        "id": "7edadfdc191a40bf",
        "type": "mqtt-broker",
        "name": "",
        "broker": "star",
        "port": "1883",
        "clientid": "",
        "autoConnect": true,
        "usetls": false,
        "protocolVersion": "4",
        "keepalive": "60",
        "cleansession": true,
        "autoUnsubscribe": true,
        "birthTopic": "",
        "birthQos": "0",
        "birthRetain": "false",
        "birthPayload": "",
        "birthMsg": {},
        "closeTopic": "",
        "closeQos": "0",
        "closeRetain": "false",
        "closePayload": "",
        "closeMsg": {},
        "willTopic": "",
        "willQos": "0",
        "willRetain": "false",
        "willPayload": "",
        "willMsg": {},
        "userProps": "",
        "sessionExpiry": ""
    },
    {
        "id": "85f3ae867011b7a8",
        "type": "ui_group",
        "name": "Timestamp",
        "tab": "f28bfc920b47689d",
        "order": 1,
        "disp": true,
        "width": "8",
        "collapse": false,
        "className": ""
    },
    {
        "id": "f28bfc920b47689d",
        "type": "ui_tab",
        "name": "SolarMeterCloud",
        "icon": "cloud",
        "order": 8,
        "disabled": false,
        "hidden": false
    }
]